balafon
